cockroachdb_mcp_server/__init__.py
cockroachdb_mcp_server/__main__.py
cockroachdb_mcp_server/cli.py
cockroachdb_mcp_server/config.py
cockroachdb_mcp_server/logging_config.py
cockroachdb_mcp_server/main.py
cockroachdb_mcp_server/schema_init.py
cockroachdb_mcp_server/server.py
cockroachdb_mcp_server/db/__init__.py
cockroachdb_mcp_server/db/db_connection.py
cockroachdb_mcp_server/models/__init__.py
cockroachdb_mcp_server/models/context.py
cockroachdb_mcp_server/routes/__init__.py
cockroachdb_mcp_server/routes/contexts.py
cockroachdb_mcp_server/routes/debug.py
cockroachdb_mcp_server/routes/health.py
cockroachdb_mcp_server-0.2.2.dist-info/licenses/LICENSE
cockroachdb_mcp_server-0.2.2.dist-info/METADATA
cockroachdb_mcp_server-0.2.2.dist-info/WHEEL
cockroachdb_mcp_server-0.2.2.dist-info/entry_points.txt
cockroachdb_mcp_server-0.2.2.dist-info/top_level.txt
cockroachdb_mcp_server-0.2.2.dist-info/RECORD
